{
  "$schema": "http://json-schema.org/draft-04/schema#",
  "title": "Fiscal Years Holder",
  "description": "A holder for current and previous fiscal years related to an order",
  "type": "object",
  "properties": {
    "current": {
      "description": "List of fiscal years associated with the order's funds",
      "type": "array",
      "items": {
        "javaType": "org.folio.rest.acq.model.finance.FiscalYear"
      }
    },
    "previous": {
      "description": "List of other available fiscal years",
      "type": "array",
      "items": {
        "javaType": "org.folio.rest.acq.model.finance.FiscalYear"
      }
    }
  },
  "required": [
    "current",
    "previous"
  ]
}
